tsaotun/__init__.py
tsaotun/cli.py
tsaotun/lib/__init__.py
tsaotun/lib/docker_client.py
tsaotun/lib/Addon/__init__.py
tsaotun/lib/Addon/loader.py
tsaotun/lib/Docker/__init__.py
tsaotun/lib/Docker/Addon/__init__.py
tsaotun/lib/Docker/Addon/command.py
tsaotun/lib/Docker/Addon/disable.py
tsaotun/lib/Docker/Addon/enable.py
tsaotun/lib/Docker/Addon/inspect.py
tsaotun/lib/Docker/Addon/install.py
tsaotun/lib/Docker/Addon/list.py
tsaotun/lib/Docker/Addon/ls.py
tsaotun/lib/Docker/Addon/placeholder.py
tsaotun/lib/Docker/Addon/rm.py
tsaotun/lib/Docker/Container/__init__.py
tsaotun/lib/Docker/Container/command.py
tsaotun/lib/Docker/Container/cp.py
tsaotun/lib/Docker/Container/create.py
tsaotun/lib/Docker/Container/exec.py
tsaotun/lib/Docker/Container/exec_create.py
tsaotun/lib/Docker/Container/exec_start.py
tsaotun/lib/Docker/Container/inspect.py
tsaotun/lib/Docker/Container/list.py
tsaotun/lib/Docker/Container/logs.py
tsaotun/lib/Docker/Container/ls.py
tsaotun/lib/Docker/Container/ps.py
tsaotun/lib/Docker/Container/rename.py
tsaotun/lib/Docker/Container/restart.py
tsaotun/lib/Docker/Container/rm.py
tsaotun/lib/Docker/Container/run.py
tsaotun/lib/Docker/Container/start.py
tsaotun/lib/Docker/Container/stats.py
tsaotun/lib/Docker/Container/stop.py
tsaotun/lib/Docker/Container/top.py
tsaotun/lib/Docker/Image/__init__.py
tsaotun/lib/Docker/Image/build.py
tsaotun/lib/Docker/Image/command.py
tsaotun/lib/Docker/Image/history.py
tsaotun/lib/Docker/Image/images.py
tsaotun/lib/Docker/Image/inspect.py
tsaotun/lib/Docker/Image/list.py
tsaotun/lib/Docker/Image/ls.py
tsaotun/lib/Docker/Image/pull.py
tsaotun/lib/Docker/Image/remove.py
tsaotun/lib/Docker/Image/rm.py
tsaotun/lib/Docker/Image/rmi.py
tsaotun/lib/Docker/Image/save.py
tsaotun/lib/Docker/Network/__init__.py
tsaotun/lib/Docker/Network/command.py
tsaotun/lib/Docker/Network/connect.py
tsaotun/lib/Docker/Network/create.py
tsaotun/lib/Docker/Network/disconnect.py
tsaotun-0.9.4.dist-info/DESCRIPTION.rst
tsaotun-0.9.4.dist-info/METADATA
tsaotun-0.9.4.dist-info/RECORD
tsaotun-0.9.4.dist-info/WHEEL
tsaotun-0.9.4.dist-info/entry_points.txt
tsaotun-0.9.4.dist-info/metadata.json
tsaotun-0.9.4.dist-info/top_level.txt
