Metadata-Version: 2.0
Name: tsaotun
Version: 0.9.4
Summary: Python based Assistance for Docker
Home-page: https://github.com/qazbnm456/tsaotun
Author: Boik Su
Author-email: boik@tdohacker.org
License: UNKNOWN
Download-URL: https://codeload.github.com/qazbnm456/tsaotun/tar.gz/0.9.4
Keywords: 0.9.4
Platform: UNKNOWN
Classifier: Environment :: Console
Classifier: Intended Audience :: Developers
Classifier: Intended Audience :: System Administrators
Classifier: License :: OSI Approved :: Apache Software License
Classifier: Topic :: Software Development
Classifier: Topic :: Terminals
Classifier: Topic :: Utilities
Classifier: Operating System :: OS Independent
Classifier: Programming Language :: Python
Classifier: Programming Language :: Python :: 2
Classifier: Programming Language :: Python :: 2.6
Classifier: Programming Language :: Python :: 2.7
Requires-Dist: GitPython (>=2.1.7)
Requires-Dist: Py-Tabwriter (>=0.1.3)
Requires-Dist: argcomplete (>=1.9.3)
Requires-Dist: arrow (>=0.12.0)
Requires-Dist: colorama (>=0.3.9)
Requires-Dist: docker (>=2.6.1)
Requires-Dist: dockerpty (>=0.4.1)
Requires-Dist: humanize (>=0.5.1)
Requires-Dist: pystache (>=0.5.4)
